LICENSE
MANIFEST.in
README.rst
setup.py
simpledist/__init__.py
simpledist/distributions.py
simpledist/kde.py
simpledist.egg-info/PKG-INFO
simpledist.egg-info/SOURCES.txt
simpledist.egg-info/dependency_links.txt
simpledist.egg-info/not-zip-safe
simpledist.egg-info/requires.txt
simpledist.egg-info/top_level.txt