Metadata-Version: 1.1
Name: simpledist
Version: 0.1.12
Summary: Defines objects useful for describing simple probability distributions.
Home-page: https://github.com/timothydmorton/simpledist
Author: Timothy D. Morton
Author-email: tim.morton@gmail.com
License: UNKNOWN
Platform: UNKNOWN
Classifier: Development Status :: 3 - Alpha
Classifier: Intended Audience :: Science/Research
Classifier: Operating System :: OS Independent
Classifier: Programming Language :: Python
Classifier: Topic :: Scientific/Engineering
